[
  {
    "date": "20260618",
    "open": 3227.717,
    "close": 3296.659,
    "high": 3311.723,
    "low": 3223.622,
    "volume": 123321739,
    "amount": 123321739,
    "change_pct": 1.6829
  },
  {
    "date": "20260622",
    "open": 3336.988,
    "close": 3349.769,
    "high": 3356.455,
    "low": 3249.67,
    "volume": 125820082,
    "amount": 125820082,
    "change_pct": 1.611
  },
  {
    "date": "20260623",
    "open": 3321.508,
    "close": 3276.326,
    "high": 3353.381,
    "low": 3235.202,
    "volume": 109364672,
    "amount": 109364672,
    "change_pct": -2.1925
  },
  {
    "date": "20260624",
    "open": 3241.55,
    "close": 3381.944,
    "high": 3384.216,
    "low": 3214.718,
    "volume": 116093443,
    "amount": 116093443,
    "change_pct": 3.2237
  },
  {
    "date": "20260625",
    "open": 3411.707,
    "close": 3442.715,
    "high": 3454.992,
    "low": 3366.693,
    "volume": 124913379,
    "amount": 124913379,
    "change_pct": 1.7969
  },
  {
    "date": "20260626",
    "open": 3408.032,
    "close": 3426.894,
    "high": 3481.708,
    "low": 3380.297,
    "volume": 143910450,
    "amount": 143910450,
    "change_pct": -0.4596
  },
  {
    "date": "20260629",
    "open": 3451.222,
    "close": 3421.558,
    "high": 3534.447,
    "low": 3290.575,
    "volume": 141653550,
    "amount": 141653550,
    "change_pct": -0.1557
  },
  {
    "date": "20260630",
    "open": 3421.9,
    "close": 3596.471,
    "high": 3599.891,
    "low": 3419.436,
    "volume": 139618870,
    "amount": 139618870,
    "change_pct": 5.1121
  },
  {
    "date": "20260701",
    "open": 3590.611,
    "close": 3559.753,
    "high": 3665.415,
    "low": 3522.636,
    "volume": 138531900,
    "amount": 138531900,
    "change_pct": -1.0209
  },
  {
    "date": "20260702",
    "open": 3424.797,
    "close": 3385.504,
    "high": 3540.159,
    "low": 3351.238,
    "volume": 137518970,
    "amount": 137518970,
    "change_pct": -4.895
  }
]